pet_vinkesh_ti/__init__.py
pet_vinkesh_ti/api_client.py
pet_vinkesh_ti/api_response.py
pet_vinkesh_ti/configuration.py
pet_vinkesh_ti/exceptions.py
pet_vinkesh_ti/py.typed
pet_vinkesh_ti/rest.py
pet_vinkesh_ti/api/__init__.py
pet_vinkesh_ti/api/pet_api.py
pet_vinkesh_ti/api/store_api.py
pet_vinkesh_ti/api/user_api.py
pet_vinkesh_ti/models/__init__.py
pet_vinkesh_ti/models/address.py
pet_vinkesh_ti/models/api_response.py
pet_vinkesh_ti/models/category.py
pet_vinkesh_ti/models/customer.py
pet_vinkesh_ti/models/order.py
pet_vinkesh_ti/models/pet.py
pet_vinkesh_ti/models/tag.py
pet_vinkesh_ti/models/user.py
pet_vinkesh_ti-0.0.1.dist-info/METADATA
pet_vinkesh_ti-0.0.1.dist-info/WHEEL
pet_vinkesh_ti-0.0.1.dist-info/top_level.txt
pet_vinkesh_ti-0.0.1.dist-info/RECORD
